mockango/__init__.py
mockango/apps.py
mockango/management/__init__.py
mockango/management/commands/__init__.py
mockango/management/commands/_private.py
mockango/management/commands/generatedata.py
mockango/tests.py
mockango/utils/__init__.py
mockango/utils/constants.py
mockango/utils/fixture.py
mockango/utils/identifiers.py
mockango/utils/providers.py
mockango-1.0.1.dist-info/LICENSE
mockango-1.0.1.dist-info/WHEEL
mockango-1.0.1.dist-info/METADATA
mockango-1.0.1.dist-info/RECORD
