Metadata-Version: 2.1
Name: mockango
Version: 1.0.1
Summary: django-admin fixture generator command
Home-page: https://github.com/iliark1382/mockango
License: BSD 3-Clause
Keywords: fixture,mock,data,django-fixture,django-admin,django,mimesis,mockango
Author: iliark1382
Author-email: iliark82@gmail.com
Requires-Python: >=3.6,<4.0
Classifier: License :: Other/Proprietary License
Classifier: Programming Language :: Python :: 3
Classifier: Programming Language :: Python :: 3.6
Classifier: Programming Language :: Python :: 3.7
Classifier: Programming Language :: Python :: 3.8
Classifier: Programming Language :: Python :: 3.9
Project-URL: Repository, https://github.com/iliark1382/mockango
